Workbook

Sheet _Lists
A1: Area_Type | B1: Confidence | C1: Status | D1: Approval_Status | E1: Property_Type | F1: Landmark_Category | G1: Source_Type | H1: Demand_Level | I1: Supply_Level | J1: Availability | K1: Yes_No | L1: Surface_Type | M1: Access_Type | N1: Record_Type
A2: Town | B2: Official | C2: Draft | D2: Approved | E2: House | F2: School | G2: Government | H2: Low | I2: Low | J2: Available | K2: Yes | L2: Paved | M2: Main Road | N2: Fard
A3: Colony | B3: Map Verified | C3: Needs Review | D3: Unapproved | E3: Plot | F3: Hospital/Clinic | G3: Map | H3: Medium | I3: Medium | J3: Reserved | K3: No | L3: Unpaved | M3: Internal Road | N3: Registry
A4: Housing Scheme | B4: Local Confirmed | C4: Verified | D4: Unknown | E4: Residential Building | F4: Mosque | G4: Local | H4: High | I4: High | J4: Sold/Closed | L4: Mixed | M4: Street | N4: Mutation/Intiqal
A5: Block | B5: Unverified | C5: Published | D5: N/A | E5: Commercial | F5: Market | G5: Portal | J5: Off Market | M5: Lane/Gali | N5: Ownership Record
A6: Revenue Area | E6: Agricultural | F6: Park | G6: Agent Observation | N6: Tax/Valuation
A7: Village/Chak | E7: Other | F7: Government Office | G7: Client Provided | N7: Other
A8: Other | F8: Transport | G8: Other
F9: Bank/ATM
F10: Shopping
F11: Other

Sheet README
A1: Chichawatni Local Property Knowledge Base
A4: Purpose | B4: Build a verified local property knowledge database for SIDDHU Property Advisor. Use it for area pages, local guides, listings, internal research, AEO/GEO and local SEO. | D4: Confidence | E4: Meaning
A5: Core hierarchy | B5: Chichawatni → Revenue Chak → Town/Colony → Block → Street/Gali → Landmark → Property | D5: Official | E5: Government / authority / official society record
A6: Rule 1 | B6: Never guess street counts, block counts, approval status, road widths, distances or property prices. | D6: Map Verified | E6: Confirmed from reliable mapping + matching context
A7: Rule 2 | B7: Every factual row should have a source URL or a clear Local Confirmed note wherever possible. | D7: Local Confirmed | E7: Confirmed by SIDDHU/local field knowledge
A8: Rule 3 | B8: Use Confidence consistently: Official, Map Verified, Local Confirmed, Unverified. | D8: Unverified | E8: Lead only — do not publish as fact
A9: Rule 4 | B9: Use Last_Verified dates. Re-check volatile data before publishing.
A10: Rule 5 | B10: Keep internal pricing/market observations private unless you explicitly decide to publish them.
A11: Recommended workflow | B11: 1) Add Area → 2) Add streets/blocks → 3) Add landmarks → 4) Add official record information → 5) Add listings → 6) Verify sources → 7) Publish only verified page content.
A12: Public-page rule | B12: Do not create thin street pages. Publish strong area pages with verified local data and real property context.

Sheet Dashboard
A1: SIDDHU Local Knowledge Dashboard
A4: Metric | B4: Value | D4: Publishing Gate | E4: Target | F4: Rule
A5: Areas entered | B5: =MAX(0,COUNTA(Areas!B:B)-1) | D5: Area page | E5: Verified or Published | F5: No thin pages; enough unique local data
A6: Verified/Published areas | B6: =COUNTIF(Areas!U:U,"Verified")+COUNTIF(Areas!U:U,"Published") | D6: Street data | E6: Official / Map Verified / Local Confirmed | F6: Do not publish guessed counts
A7: Street / Block records | B7: =MAX(0,COUNTA(Streets_Blocks!A:A)-1) | D7: Approval/legal status | E7: Official source only | F7: Always store source URL + verified date
A8: Landmarks | B8: =MAX(0,COUNTA(Landmarks!A:A)-1) | D8: Market data | E8: Internal unless approved | F8: Do not confuse asking price with official valuation
A9: Active listings | B9: =COUNTIF(Listings!T:T,"Available")

Sheet Areas
A1: Area_ID | B1: Area_Name | C1: Alternate_Name | D1: Area_Type | E1: Parent_Chak | F1: Tehsil | G1: District | H1: Province | I1: Postal_Code | J1: Main_Access_Road | K1: Nearby_Areas | L1: Residential_Character | M1: Common_House_Sizes | N1: Utilities_Status | O1: Approval_Status | P1: Approval_Source_URL | Q1: Map_URL | R1: Latitude | S1: Longitude | T1: Data_Confidence | U1: Last_Verified | V1: Status | W1: Notes | X1: Completeness_% | Z1: One row per town/colony/revenue area. Use Area_ID as the parent key everywhere.
X2: =IF(B2="","",ROUND(COUNTA(B2,D2,E2,J2,K2,L2,M2,N2,O2,P2,Q2,T2,U2,V2)/14*100,0))
X3: =IF(B3="","",ROUND(COUNTA(B3,D3,E3,J3,K3,L3,M3,N3,O3,P3,Q3,T3,U3,V3)/14*100,0))
X4: =IF(B4="","",ROUND(COUNTA(B4,D4,E4,J4,K4,L4,M4,N4,O4,P4,Q4,T4,U4,V4)/14*100,0))
X5: =IF(B5="","",ROUND(COUNTA(B5,D5,E5,J5,K5,L5,M5,N5,O5,P5,Q5,T5,U5,V5)/14*100,0))
X6: =IF(B6="","",ROUND(COUNTA(B6,D6,E6,J6,K6,L6,M6,N6,O6,P6,Q6,T6,U6,V6)/14*100,0))
X7: =IF(B7="","",ROUND(COUNTA(B7,D7,E7,J7,K7,L7,M7,N7,O7,P7,Q7,T7,U7,V7)/14*100,0))
X8: =IF(B8="","",ROUND(COUNTA(B8,D8,E8,J8,K8,L8,M8,N8,O8,P8,Q8,T8,U8,V8)/14*100,0))
X9: =IF(B9="","",ROUND(COUNTA(B9,D9,E9,J9,K9,L9,M9,N9,O9,P9,Q9,T9,U9,V9)/14*100,0))
X10: =IF(B10="","",ROUND(COUNTA(B10,D10,E10,J10,K10,L10,M10,N10,O10,P10,Q10,T10,U10,V10)/14*100,0))
X11: =IF(B11="","",ROUND(COUNTA(B11,D11,E11,J11,K11,L11,M11,N11,O11,P11,Q11,T11,U11,V11)/14*100,0))
X12: =IF(B12="","",ROUND(COUNTA(B12,D12,E12,J12,K12,L12,M12,N12,O12,P12,Q12,T12,U12,V12)/14*100,0))
X13: =IF(B13="","",ROUND(COUNTA(B13,D13,E13,J13,K13,L13,M13,N13,O13,P13,Q13,T13,U13,V13)/14*100,0))
... X500: =IF(B500="","",ROUND(COUNTA(B500,D500,E500,J500,K500,L500,M500,N500,O500,P500,Q500,T500,U500,V500)/14*100,0))

Sheet Streets_Blocks
A1: Location_ID | B1: Area_ID | C1: Block_Name | D1: Street_No | E1: Gali_Name | F1: Road_Name | G1: Street_Width_ft | H1: Surface_Type | I1: Access_Type | J1: Nearby_Landmark | K1: Latitude | L1: Longitude | M1: Map_URL | N1: Source_URL | O1: Confidence | P1: Last_Verified | Q1: Notes | Z1: One row per verified street, gali, block or named road segment.

Sheet Landmarks
A1: Landmark_ID | B1: Area_ID | C1: Landmark_Name | D1: Category | E1: Address | F1: Nearby_Street | G1: Approx_Distance_m | H1: Map_URL | I1: Source_URL | J1: Confidence | K1: Last_Verified | L1: Notes | Z1: Only add real landmarks relevant to property decisions.

Sheet Property_Records
A1: Record_ID | B1: Area_ID | C1: Authority | D1: Record_Type | E1: Office_Name | F1: Office_Address | G1: Official_URL | H1: Contact | I1: Verification_Process | J1: Required_Documents | K1: Source_URL | L1: Confidence | M1: Last_Verified | N1: Notes | Z1: Store official record/authority guidance and sources. Do not imply legal guarantees.

Sheet Market_Data
A1: Market_ID | B1: Area_ID | C1: Observation_Date | D1: Property_Type | E1: Size_Marla | F1: Demand_Level | G1: Supply_Level | H1: Typical_Time_To_Sell_Days | I1: Observed_Ask_Min_PKR | J1: Observed_Ask_Max_PKR | K1: Transactions_Observed | L1: Source_Type | M1: Source_URL | N1: Confidence | O1: Public_Display | P1: Notes | Z1: Internal market observations. Asking price ≠ sold price ≠ official valuation.

Sheet Listings
A1: Property_ID | B1: Area_ID | C1: Street_or_Block | D1: Listing_Title | E1: Property_Type | F1: Size_Marla | G1: Bedrooms | H1: Bathrooms | I1: Floors | J1: Condition | K1: Corner | L1: Parking | M1: Road_Width_ft | N1: Utilities | O1: Image_Folder | P1: Video_URL | Q1: Map_URL | R1: Public_Price_Display | S1: Internal_Ask_Price_PKR | T1: Availability | U1: Last_Verified | V1: Notes | Z1: Use real property data/photos only. Public_Price_Display can remain No.

Sheet Sources
A1: Source_ID | B1: Source_Name | C1: Source_Type | D1: URL | E1: Coverage | F1: Reliability | G1: Last_Checked | H1: Notes | Z1: Central registry of government, map, local and portal sources.
